myMLpack/__init__.py
myMLpack/try.py
ML_exam-0.0.5.dist-info/LICENSE
ML_exam-0.0.5.dist-info/METADATA
ML_exam-0.0.5.dist-info/WHEEL
ML_exam-0.0.5.dist-info/top_level.txt
ML_exam-0.0.5.dist-info/RECORD
