Metadata-Version: 2.1
Name: ML-exam
Version: 0.0.5
Summary: ML Exam trial
Home-page: https://github.com/pypa/sampleproject
Author: Amaan Ansari
Author-email: m.amaan02@gmail.com
Project-URL: Bug Tracker, https://github.com/pypa/sampleproject/issues
Classifier: Programming Language :: Python :: 3
Classifier: License :: OSI Approved :: MIT License
Classifier: Operating System :: OS Independent
Requires-Python: >=3.6
License-File: LICENSE
Requires-Dist: numpy
